pygaggle/__init__.py
pygaggle/logger.py
pygaggle/settings.py
pygaggle/data/__init__.py
pygaggle/data/kaggle.py
pygaggle/data/relevance.py
pygaggle/model/__init__.py
pygaggle/model/decode.py
pygaggle/model/encode.py
pygaggle/model/evaluate.py
pygaggle/model/serialize.py
pygaggle/model/tokenize.py
pygaggle/rerank/__init__.py
pygaggle/rerank/base.py
pygaggle/rerank/bm25.py
pygaggle/rerank/random.py
pygaggle/rerank/similarity.py
pygaggle/rerank/transformer.py
pygaggle/run/__init__.py
pygaggle/run/args.py
pygaggle/run/evaluate_kaggle_highlighter.py
tests/__init__.py
tests/test_base.py
pygaggle-0.0.1.dist-info/LICENSE
pygaggle-0.0.1.dist-info/METADATA
pygaggle-0.0.1.dist-info/WHEEL
pygaggle-0.0.1.dist-info/top_level.txt
pygaggle-0.0.1.dist-info/RECORD
