Metadata-Version: 2.1
Name: pygaggle
Version: 0.0.1
Summary: A gaggle of rerankers for CovidQA and CORD-19
Home-page: https://github.com/castorini/pygaggle
Author: PyGaggle Gaggle
Author-email: r33tang@uwaterloo.ca
License: UNKNOWN
Platform: UNKNOWN
Classifier: Programming Language :: Python :: 3
Classifier: License :: OSI Approved :: Apache Software License
Classifier: Operating System :: OS Independent
Requires-Python: >=3.7
Requires-Dist: coloredlogs (==14.0)
Requires-Dist: numpy (==1.18.2)
Requires-Dist: pydantic (==1.5)
Requires-Dist: pyserini (==0.9.0.0)
Requires-Dist: scikit-learn (>=0.22)
Requires-Dist: scipy (>=1.4)
Requires-Dist: spacy (==2.2.4)
Requires-Dist: tensorboard (>=2.1.0)
Requires-Dist: tensorflow (>=2.2.0rc1)
Requires-Dist: tokenizers (==0.5.2)
Requires-Dist: tqdm (==4.45.0)
Requires-Dist: transformers (==2.7.0)
